chara/__init__.py
chara/common/__init__.py
chara/common/sample_files.py
chara/common/cache/__init__.py
chara/common/cache/core/__init__.py
chara/common/cache/core/cache.py
chara/common/cache/core/cache_entity.py
chara/common/cache/core/dict_cache.py
chara/common/cache/core/list_cache.py
chara/common/cache/core/segmented_cache.py
chara/common/cache/files/__init__.py
chara/common/cache/files/file_cache.py
chara/common/cache/files/jsonl_cache.py
chara/common/cache/files/tempfile_cache.py
chara/common/cache/folders/__init__.py
chara/common/cache/folders/folder_cache.py
chara/common/cache/folders/multifile_cache.py
chara/common/descriptions/__init__.py
chara/common/descriptions/language/__init__.py
chara/common/descriptions/language/english.py
chara/common/descriptions/language/german.py
chara/common/descriptions/language/language.py
chara/common/descriptions/language/russian.py
chara/common/descriptions/language/standardizer.py
chara/common/descriptions/language/upsampling_dataset/__init__.py
chara/common/descriptions/language/upsampling_dataset/english.py
chara/common/descriptions/language/upsampling_dataset/german.py
chara/common/files/voice/lina1.wav
chara/common/files/voice/lina2.wav
chara/common/files/voice/lina3.wav
chara/common/logging/__init__.py
chara/common/logging/image_log.py
chara/common/logging/ipywidgets_log.py
chara/common/logging/log_item.py
chara/common/logging/logger_class.py
chara/common/logging/matplotlib_log.py
chara/common/logging/pandas_log.py
chara/common/logging/simple.py
chara/common/pipelines/__init__.py
chara/common/pipelines/apis.py
chara/common/pipelines/logger_definition.py
chara/common/pipelines/annotation/__init__.py
chara/common/pipelines/annotation/core/__init__.py
chara/common/pipelines/annotation/core/annotation_cache.py
chara/common/pipelines/annotation/core/annotation_unit.py
chara/common/pipelines/annotation/core/annotator.py
chara/common/pipelines/annotation/core/task_planner.py
kaia_chara-4.0.9.dist-info/METADATA
kaia_chara-4.0.9.dist-info/WHEEL
kaia_chara-4.0.9.dist-info/top_level.txt
kaia_chara-4.0.9.dist-info/RECORD
