Metadata-Version: 2.4
Name: kaia-chara
Version: 4.0.9
Summary: ML-Pipelines architecture and implementation for paraphrasing and voice cloning
Author-email: Yuri Okulovsky <yuri.okulovsky@gmail.com>
License-Expression: LGPL-3.0-or-later
Project-URL: repository, https://github.com/okulovsky/kaia/tree/main/avatar
Classifier: Programming Language :: Python :: 3.10
Classifier: Programming Language :: Python :: 3.11
Classifier: Programming Language :: Python :: 3.12
Classifier: Programming Language :: Python :: 3.13
Classifier: Intended Audience :: Developers
Classifier: Intended Audience :: Science/Research
Classifier: Intended Audience :: Information Technology
Classifier: Topic :: Scientific/Engineering :: Artificial Intelligence
Classifier: Development Status :: 4 - Beta
Requires-Python: <4.0,>=3.10
Requires-Dist: yo_fluq
Requires-Dist: kaia-foundation
Requires-Dist: kaia-brainbox
Requires-Dist: kaia-eaglesong
Requires-Dist: kaia-grammatron
Requires-Dist: kaia-avatar
Requires-Dist: flask
Requires-Dist: loguru
Requires-Dist: matplotlib
Requires-Dist: ipywidgets
Requires-Dist: gradio
Requires-Dist: python-Levenshtein
Provides-Extra: dev
Requires-Dist: tox; extra == "dev"
Requires-Dist: tox-conda; extra == "dev"
Requires-Dist: twine; extra == "dev"
